thundersvm/__init__.py
thundersvm/libthundersvm.so
thundersvm/thundersvm.py
thundersvm_cpu-0.3.3.dist-info/METADATA
thundersvm_cpu-0.3.3.dist-info/WHEEL
thundersvm_cpu-0.3.3.dist-info/top_level.txt
thundersvm_cpu-0.3.3.dist-info/RECORD
