Metadata-Version: 2.1
Name: thundersvm-cpu
Version: 0.3.3
Summary: A Fast SVM Library on GPUs and CPUs
Home-page: https://github.com/zeyiwen/thundersvm
License: UNKNOWN
Platform: UNKNOWN
Classifier: Programming Language :: Python :: 3
Classifier: License :: OSI Approved :: Apache Software License
Requires-Python: >=3
Requires-Dist: numpy
Requires-Dist: scipy
Requires-Dist: scikit-learn
